my_interface/__init__.py
my_interface/parent_interface.py
obfuscate_python-0.1.dist-info/LICENSE
obfuscate_python-0.1.dist-info/METADATA
obfuscate_python-0.1.dist-info/WHEEL
obfuscate_python-0.1.dist-info/top_level.txt
obfuscate_python-0.1.dist-info/RECORD
