Metadata-Version: 2.1
Name: obfuscate-python
Version: 0.1
Summary: A package containing ParentInterface class
Home-page: https://github.com/nitinsuvagia/obfuscate-python
Author: Nitin
Author-email: nitin@softqubes.com
License: UNKNOWN
Platform: UNKNOWN
Classifier: Programming Language :: Python :: 3
Classifier: License :: OSI Approved :: MIT License
Classifier: Operating System :: OS Independent
License-File: LICENSE
